camsai/__init__.py
camsai/standards/__init__.py
camsai/standards/jarvisnist/__init__.py
camsai/standards/mat3ra/__init__.py
camsai_standards-2024.12.13.post1.dist-info/LICENSE
camsai_standards-2024.12.13.post1.dist-info/METADATA
camsai_standards-2024.12.13.post1.dist-info/WHEEL
camsai_standards-2024.12.13.post1.dist-info/top_level.txt
camsai_standards-2024.12.13.post1.dist-info/RECORD
